litei2c/__init__.py
litei2c/clkgen.py
litei2c/common.py
litei2c/crossbar.py
litei2c-2024.12.dist-info/licenses/LICENSE
litei2c-2024.12.dist-info/METADATA
litei2c-2024.12.dist-info/WHEEL
litei2c-2024.12.dist-info/top_level.txt
litei2c-2024.12.dist-info/RECORD
