Metadata-Version: 2.4
Name: litei2c
Version: 2024.12
Summary: Small footprint and configurable I2C core
Home-page: https://github.com/litex-hub
Download-URL: https://github.com/litex-hub/litei2c
Author: LiteI2C Developers
License: BSD
Keywords: HDL ASIC FPGA hardware design
Classifier: Topic :: Scientific/Engineering :: Electronic Design Automation (EDA)
Classifier: Environment :: Console
Classifier: Development Status :: 3 - Alpha
Classifier: Intended Audience :: Developers
Classifier: License :: OSI Approved :: BSD License
Classifier: Operating System :: OS Independent
Classifier: Programming Language :: Python
Requires-Python: ~=3.7
License-File: LICENSE
Requires-Dist: migen
Requires-Dist: litex
Provides-Extra: develop
Requires-Dist: mesonpexpectsetuptoolsrequests; extra == "develop"
Dynamic: author
Dynamic: classifier
Dynamic: description
Dynamic: description-content-type
Dynamic: download-url
Dynamic: home-page
Dynamic: keywords
Dynamic: license
Dynamic: license-file
Dynamic: provides-extra
Dynamic: requires-dist
Dynamic: requires-python
Dynamic: summary
